{
	"archive" : {},
	"artifacts" : 
	[
		{
			"path" : "storage/innobase/libinnobase_embedded.a"
		}
	],
	"backtrace" : 3,
	"backtraceGraph" : 
	{
		"commands" : 
		[
			"ADD_LIBRARY",
			"ADD_CONVENIENCE_LIBRARY",
			"MYSQL_ADD_PLUGIN",
			"ADD_DEPENDENCIES",
			"ADD_DEFINITIONS",
			"INCLUDE_DIRECTORIES"
		],
		"files" : 
		[
			"cmake/libutils.cmake",
			"cmake/plugin.cmake",
			"storage/innobase/CMakeLists.txt",
			"CMakeLists.txt"
		],
		"nodes" : 
		[
			{
				"file" : 2
			},
			{
				"command" : 2,
				"file" : 2,
				"line" : 430,
				"parent" : 0
			},
			{
				"command" : 1,
				"file" : 1,
				"line" : 126,
				"parent" : 1
			},
			{
				"command" : 0,
				"file" : 0,
				"line" : 103,
				"parent" : 2
			},
			{
				"command" : 3,
				"file" : 1,
				"line" : 132,
				"parent" : 1
			},
			{
				"command" : 4,
				"file" : 2,
				"line" : 193,
				"parent" : 0
			},
			{
				"command" : 4,
				"file" : 2,
				"line" : 151,
				"parent" : 0
			},
			{
				"command" : 4,
				"file" : 2,
				"line" : 159,
				"parent" : 0
			},
			{
				"command" : 4,
				"file" : 2,
				"line" : 155,
				"parent" : 0
			},
			{
				"command" : 4,
				"file" : 2,
				"line" : 167,
				"parent" : 0
			},
			{
				"command" : 4,
				"file" : 2,
				"line" : 163,
				"parent" : 0
			},
			{
				"command" : 4,
				"file" : 2,
				"line" : 29,
				"parent" : 0
			},
			{
				"command" : 4,
				"file" : 2,
				"line" : 278,
				"parent" : 0
			},
			{
				"file" : 3
			},
			{
				"command" : 5,
				"file" : 3,
				"line" : 420,
				"parent" : 13
			},
			{
				"command" : 5,
				"file" : 2,
				"line" : 288,
				"parent" : 0
			},
			{
				"command" : 5,
				"file" : 1,
				"line" : 55,
				"parent" : 1
			}
		]
	},
	"compileGroups" : 
	[
		{
			"compileCommandFragments" : 
			[
				{
					"fragment" : " -Wall -Wno-null-conversion -Wno-unused-private-field -g -DENABLED_DEBUG_SYNC -DUNIV_DEBUG -DUNIV_SYNC_DEBUG   -DUNIV_LINUX -D_GNU_SOURCE=1"
				},
				{
					"fragment" : "-fPIC"
				}
			],
			"defines" : 
			[
				{
					"define" : "HAVE_CONFIG_H"
				},
				{
					"backtrace" : 5,
					"define" : "HAVE_IB_ATOMIC_PTHREAD_T_GCC=1"
				},
				{
					"backtrace" : 6,
					"define" : "HAVE_IB_GCC_ATOMIC_BUILTINS=1"
				},
				{
					"backtrace" : 7,
					"define" : "HAVE_IB_GCC_ATOMIC_BUILTINS_64=1"
				},
				{
					"backtrace" : 8,
					"define" : "HAVE_IB_GCC_ATOMIC_BUILTINS_BYTE=1"
				},
				{
					"backtrace" : 9,
					"define" : "HAVE_IB_GCC_ATOMIC_THREAD_FENCE=1"
				},
				{
					"backtrace" : 10,
					"define" : "HAVE_IB_GCC_SYNC_SYNCHRONISE=1"
				},
				{
					"backtrace" : 11,
					"define" : "LINUX_NATIVE_AIO=1"
				},
				{
					"backtrace" : 12,
					"define" : "SIZEOF_PTHREAD_T=8"
				}
			],
			"includes" : 
			[
				{
					"backtrace" : 14,
					"path" : "/home/caizhw3/code/mysql-5.6.21/build/include"
				},
				{
					"backtrace" : 15,
					"path" : "/home/caizhw3/code/mysql-5.6.21/storage/innobase/include"
				},
				{
					"backtrace" : 15,
					"path" : "/home/caizhw3/code/mysql-5.6.21/storage/innobase/handler"
				},
				{
					"backtrace" : 16,
					"path" : "/home/caizhw3/code/mysql-5.6.21/include"
				},
				{
					"backtrace" : 16,
					"path" : "/home/caizhw3/code/mysql-5.6.21/sql"
				},
				{
					"backtrace" : 16,
					"path" : "/home/caizhw3/code/mysql-5.6.21/regex"
				},
				{
					"backtrace" : 16,
					"path" : "/home/caizhw3/code/mysql-5.6.21/extra/yassl/include"
				},
				{
					"backtrace" : 16,
					"path" : "/home/caizhw3/code/mysql-5.6.21/extra/yassl/taocrypt/include"
				},
				{
					"backtrace" : 16,
					"path" : "/home/caizhw3/code/mysql-5.6.21/zlib"
				}
			],
			"language" : "CXX",
			"sourceIndexes" : 
			[
				0,
				1,
				2,
				3,
				4,
				5,
				6,
				7,
				8,
				9,
				10,
				11,
				12,
				13,
				14,
				15,
				16,
				17,
				18,
				19,
				20,
				21,
				22,
				23,
				24,
				25,
				26,
				27,
				28,
				29,
				30,
				31,
				32,
				33,
				34,
				35,
				36,
				37,
				38,
				39,
				40,
				41,
				42,
				43,
				44,
				45,
				46,
				47,
				48,
				49,
				50,
				51,
				52,
				53,
				54,
				55,
				56,
				57,
				58,
				59,
				60,
				61,
				62,
				63,
				64,
				65,
				66,
				67,
				68,
				69,
				70,
				71,
				72,
				73,
				74,
				75,
				76,
				77,
				78,
				79,
				80,
				81,
				82,
				83,
				84,
				85,
				86,
				87,
				88,
				89,
				90,
				91,
				92,
				93,
				94,
				95,
				96,
				97,
				98,
				99,
				100,
				101,
				102,
				103,
				104,
				105,
				106,
				107,
				108,
				109,
				110,
				111,
				112,
				113,
				114
			]
		}
	],
	"dependencies" : 
	[
		{
			"backtrace" : 4,
			"id" : "GenError::@fd08edcdee322cedcc5e"
		}
	],
	"id" : "innobase_embedded::@8123eafe19b66234b7de",
	"name" : "innobase_embedded",
	"nameOnDisk" : "libinnobase_embedded.a",
	"paths" : 
	{
		"build" : "storage/innobase",
		"source" : "storage/innobase"
	},
	"sourceGroups" : 
	[
		{
			"name" : "Source Files",
			"sourceIndexes" : 
			[
				0,
				1,
				2,
				3,
				4,
				5,
				6,
				7,
				8,
				9,
				10,
				11,
				12,
				13,
				14,
				15,
				16,
				17,
				18,
				19,
				20,
				21,
				22,
				23,
				24,
				25,
				26,
				27,
				28,
				29,
				30,
				31,
				32,
				33,
				34,
				35,
				36,
				37,
				38,
				39,
				40,
				41,
				42,
				43,
				44,
				45,
				46,
				47,
				48,
				49,
				50,
				51,
				52,
				53,
				54,
				55,
				56,
				57,
				58,
				59,
				60,
				61,
				62,
				63,
				64,
				65,
				66,
				67,
				68,
				69,
				70,
				71,
				72,
				73,
				74,
				75,
				76,
				77,
				78,
				79,
				80,
				81,
				82,
				83,
				84,
				85,
				86,
				87,
				88,
				89,
				90,
				91,
				92,
				93,
				94,
				95,
				96,
				97,
				98,
				99,
				100,
				101,
				102,
				103,
				104,
				105,
				106,
				107,
				108,
				109,
				110,
				111,
				112,
				113,
				114
			]
		}
	],
	"sources" : 
	[
		{
			"backtrace" : 3,
			"compileGroupIndex" : 0,
			"path" : "storage/innobase/api/api0api.cc",
			"sourceGroupIndex" : 0
		},
		{
			"backtrace" : 3,
			"compileGroupIndex" : 0,
			"path" : "storage/innobase/api/api0misc.cc",
			"sourceGroupIndex" : 0
		},
		{
			"backtrace" : 3,
			"compileGroupIndex" : 0,
			"path" : "storage/innobase/btr/btr0btr.cc",
			"sourceGroupIndex" : 0
		},
		{
			"backtrace" : 3,
			"compileGroupIndex" : 0,
			"path" : "storage/innobase/btr/btr0cur.cc",
			"sourceGroupIndex" : 0
		},
		{
			"backtrace" : 3,
			"compileGroupIndex" : 0,
			"path" : "storage/innobase/btr/btr0pcur.cc",
			"sourceGroupIndex" : 0
		},
		{
			"backtrace" : 3,
			"compileGroupIndex" : 0,
			"path" : "storage/innobase/btr/btr0sea.cc",
			"sourceGroupIndex" : 0
		},
		{
			"backtrace" : 3,
			"compileGroupIndex" : 0,
			"path" : "storage/innobase/buf/buf0buddy.cc",
			"sourceGroupIndex" : 0
		},
		{
			"backtrace" : 3,
			"compileGroupIndex" : 0,
			"path" : "storage/innobase/buf/buf0buf.cc",
			"sourceGroupIndex" : 0
		},
		{
			"backtrace" : 3,
			"compileGroupIndex" : 0,
			"path" : "storage/innobase/buf/buf0dblwr.cc",
			"sourceGroupIndex" : 0
		},
		{
			"backtrace" : 3,
			"compileGroupIndex" : 0,
			"path" : "storage/innobase/buf/buf0checksum.cc",
			"sourceGroupIndex" : 0
		},
		{
			"backtrace" : 3,
			"compileGroupIndex" : 0,
			"path" : "storage/innobase/buf/buf0dump.cc",
			"sourceGroupIndex" : 0
		},
		{
			"backtrace" : 3,
			"compileGroupIndex" : 0,
			"path" : "storage/innobase/buf/buf0flu.cc",
			"sourceGroupIndex" : 0
		},
		{
			"backtrace" : 3,
			"compileGroupIndex" : 0,
			"path" : "storage/innobase/buf/buf0lru.cc",
			"sourceGroupIndex" : 0
		},
		{
			"backtrace" : 3,
			"compileGroupIndex" : 0,
			"path" : "storage/innobase/buf/buf0rea.cc",
			"sourceGroupIndex" : 0
		},
		{
			"backtrace" : 3,
			"compileGroupIndex" : 0,
			"path" : "storage/innobase/data/data0data.cc",
			"sourceGroupIndex" : 0
		},
		{
			"backtrace" : 3,
			"compileGroupIndex" : 0,
			"path" : "storage/innobase/data/data0type.cc",
			"sourceGroupIndex" : 0
		},
		{
			"backtrace" : 3,
			"compileGroupIndex" : 0,
			"path" : "storage/innobase/dict/dict0boot.cc",
			"sourceGroupIndex" : 0
		},
		{
			"backtrace" : 3,
			"compileGroupIndex" : 0,
			"path" : "storage/innobase/dict/dict0crea.cc",
			"sourceGroupIndex" : 0
		},
		{
			"backtrace" : 3,
			"compileGroupIndex" : 0,
			"path" : "storage/innobase/dict/dict0dict.cc",
			"sourceGroupIndex" : 0
		},
		{
			"backtrace" : 3,
			"compileGroupIndex" : 0,
			"path" : "storage/innobase/dict/dict0load.cc",
			"sourceGroupIndex" : 0
		},
		{
			"backtrace" : 3,
			"compileGroupIndex" : 0,
			"path" : "storage/innobase/dict/dict0mem.cc",
			"sourceGroupIndex" : 0
		},
		{
			"backtrace" : 3,
			"compileGroupIndex" : 0,
			"path" : "storage/innobase/dict/dict0stats.cc",
			"sourceGroupIndex" : 0
		},
		{
			"backtrace" : 3,
			"compileGroupIndex" : 0,
			"path" : "storage/innobase/dict/dict0stats_bg.cc",
			"sourceGroupIndex" : 0
		},
		{
			"backtrace" : 3,
			"compileGroupIndex" : 0,
			"path" : "storage/innobase/dyn/dyn0dyn.cc",
			"sourceGroupIndex" : 0
		},
		{
			"backtrace" : 3,
			"compileGroupIndex" : 0,
			"path" : "storage/innobase/eval/eval0eval.cc",
			"sourceGroupIndex" : 0
		},
		{
			"backtrace" : 3,
			"compileGroupIndex" : 0,
			"path" : "storage/innobase/eval/eval0proc.cc",
			"sourceGroupIndex" : 0
		},
		{
			"backtrace" : 3,
			"compileGroupIndex" : 0,
			"path" : "storage/innobase/fil/fil0fil.cc",
			"sourceGroupIndex" : 0
		},
		{
			"backtrace" : 3,
			"compileGroupIndex" : 0,
			"path" : "storage/innobase/fsp/fsp0fsp.cc",
			"sourceGroupIndex" : 0
		},
		{
			"backtrace" : 3,
			"compileGroupIndex" : 0,
			"path" : "storage/innobase/fut/fut0fut.cc",
			"sourceGroupIndex" : 0
		},
		{
			"backtrace" : 3,
			"compileGroupIndex" : 0,
			"path" : "storage/innobase/fut/fut0lst.cc",
			"sourceGroupIndex" : 0
		},
		{
			"backtrace" : 3,
			"compileGroupIndex" : 0,
			"path" : "storage/innobase/ha/ha0ha.cc",
			"sourceGroupIndex" : 0
		},
		{
			"backtrace" : 3,
			"compileGroupIndex" : 0,
			"path" : "storage/innobase/ha/ha0storage.cc",
			"sourceGroupIndex" : 0
		},
		{
			"backtrace" : 3,
			"compileGroupIndex" : 0,
			"path" : "storage/innobase/ha/hash0hash.cc",
			"sourceGroupIndex" : 0
		},
		{
			"backtrace" : 3,
			"compileGroupIndex" : 0,
			"path" : "storage/innobase/fts/fts0fts.cc",
			"sourceGroupIndex" : 0
		},
		{
			"backtrace" : 3,
			"compileGroupIndex" : 0,
			"path" : "storage/innobase/fts/fts0ast.cc",
			"sourceGroupIndex" : 0
		},
		{
			"backtrace" : 3,
			"compileGroupIndex" : 0,
			"path" : "storage/innobase/fts/fts0blex.cc",
			"sourceGroupIndex" : 0
		},
		{
			"backtrace" : 3,
			"compileGroupIndex" : 0,
			"path" : "storage/innobase/fts/fts0config.cc",
			"sourceGroupIndex" : 0
		},
		{
			"backtrace" : 3,
			"compileGroupIndex" : 0,
			"path" : "storage/innobase/fts/fts0opt.cc",
			"sourceGroupIndex" : 0
		},
		{
			"backtrace" : 3,
			"compileGroupIndex" : 0,
			"path" : "storage/innobase/fts/fts0pars.cc",
			"sourceGroupIndex" : 0
		},
		{
			"backtrace" : 3,
			"compileGroupIndex" : 0,
			"path" : "storage/innobase/fts/fts0que.cc",
			"sourceGroupIndex" : 0
		},
		{
			"backtrace" : 3,
			"compileGroupIndex" : 0,
			"path" : "storage/innobase/fts/fts0sql.cc",
			"sourceGroupIndex" : 0
		},
		{
			"backtrace" : 3,
			"compileGroupIndex" : 0,
			"path" : "storage/innobase/fts/fts0tlex.cc",
			"sourceGroupIndex" : 0
		},
		{
			"backtrace" : 3,
			"compileGroupIndex" : 0,
			"path" : "storage/innobase/handler/ha_innodb.cc",
			"sourceGroupIndex" : 0
		},
		{
			"backtrace" : 3,
			"compileGroupIndex" : 0,
			"path" : "storage/innobase/handler/handler0alter.cc",
			"sourceGroupIndex" : 0
		},
		{
			"backtrace" : 3,
			"compileGroupIndex" : 0,
			"path" : "storage/innobase/handler/i_s.cc",
			"sourceGroupIndex" : 0
		},
		{
			"backtrace" : 3,
			"compileGroupIndex" : 0,
			"path" : "storage/innobase/ibuf/ibuf0ibuf.cc",
			"sourceGroupIndex" : 0
		},
		{
			"backtrace" : 3,
			"compileGroupIndex" : 0,
			"path" : "storage/innobase/lock/lock0iter.cc",
			"sourceGroupIndex" : 0
		},
		{
			"backtrace" : 3,
			"compileGroupIndex" : 0,
			"path" : "storage/innobase/lock/lock0lock.cc",
			"sourceGroupIndex" : 0
		},
		{
			"backtrace" : 3,
			"compileGroupIndex" : 0,
			"path" : "storage/innobase/lock/lock0wait.cc",
			"sourceGroupIndex" : 0
		},
		{
			"backtrace" : 3,
			"compileGroupIndex" : 0,
			"path" : "storage/innobase/log/log0log.cc",
			"sourceGroupIndex" : 0
		},
		{
			"backtrace" : 3,
			"compileGroupIndex" : 0,
			"path" : "storage/innobase/log/log0recv.cc",
			"sourceGroupIndex" : 0
		},
		{
			"backtrace" : 3,
			"compileGroupIndex" : 0,
			"path" : "storage/innobase/mach/mach0data.cc",
			"sourceGroupIndex" : 0
		},
		{
			"backtrace" : 3,
			"compileGroupIndex" : 0,
			"path" : "storage/innobase/mem/mem0mem.cc",
			"sourceGroupIndex" : 0
		},
		{
			"backtrace" : 3,
			"compileGroupIndex" : 0,
			"path" : "storage/innobase/mem/mem0pool.cc",
			"sourceGroupIndex" : 0
		},
		{
			"backtrace" : 3,
			"compileGroupIndex" : 0,
			"path" : "storage/innobase/mtr/mtr0log.cc",
			"sourceGroupIndex" : 0
		},
		{
			"backtrace" : 3,
			"compileGroupIndex" : 0,
			"path" : "storage/innobase/mtr/mtr0mtr.cc",
			"sourceGroupIndex" : 0
		},
		{
			"backtrace" : 3,
			"compileGroupIndex" : 0,
			"path" : "storage/innobase/os/os0file.cc",
			"sourceGroupIndex" : 0
		},
		{
			"backtrace" : 3,
			"compileGroupIndex" : 0,
			"path" : "storage/innobase/os/os0proc.cc",
			"sourceGroupIndex" : 0
		},
		{
			"backtrace" : 3,
			"compileGroupIndex" : 0,
			"path" : "storage/innobase/os/os0sync.cc",
			"sourceGroupIndex" : 0
		},
		{
			"backtrace" : 3,
			"compileGroupIndex" : 0,
			"path" : "storage/innobase/os/os0thread.cc",
			"sourceGroupIndex" : 0
		},
		{
			"backtrace" : 3,
			"compileGroupIndex" : 0,
			"path" : "storage/innobase/page/page0cur.cc",
			"sourceGroupIndex" : 0
		},
		{
			"backtrace" : 3,
			"compileGroupIndex" : 0,
			"path" : "storage/innobase/page/page0page.cc",
			"sourceGroupIndex" : 0
		},
		{
			"backtrace" : 3,
			"compileGroupIndex" : 0,
			"path" : "storage/innobase/page/page0zip.cc",
			"sourceGroupIndex" : 0
		},
		{
			"backtrace" : 3,
			"compileGroupIndex" : 0,
			"path" : "storage/innobase/pars/lexyy.cc",
			"sourceGroupIndex" : 0
		},
		{
			"backtrace" : 3,
			"compileGroupIndex" : 0,
			"path" : "storage/innobase/pars/pars0grm.cc",
			"sourceGroupIndex" : 0
		},
		{
			"backtrace" : 3,
			"compileGroupIndex" : 0,
			"path" : "storage/innobase/pars/pars0opt.cc",
			"sourceGroupIndex" : 0
		},
		{
			"backtrace" : 3,
			"compileGroupIndex" : 0,
			"path" : "storage/innobase/pars/pars0pars.cc",
			"sourceGroupIndex" : 0
		},
		{
			"backtrace" : 3,
			"compileGroupIndex" : 0,
			"path" : "storage/innobase/pars/pars0sym.cc",
			"sourceGroupIndex" : 0
		},
		{
			"backtrace" : 3,
			"compileGroupIndex" : 0,
			"path" : "storage/innobase/que/que0que.cc",
			"sourceGroupIndex" : 0
		},
		{
			"backtrace" : 3,
			"compileGroupIndex" : 0,
			"path" : "storage/innobase/read/read0read.cc",
			"sourceGroupIndex" : 0
		},
		{
			"backtrace" : 3,
			"compileGroupIndex" : 0,
			"path" : "storage/innobase/rem/rem0cmp.cc",
			"sourceGroupIndex" : 0
		},
		{
			"backtrace" : 3,
			"compileGroupIndex" : 0,
			"path" : "storage/innobase/rem/rem0rec.cc",
			"sourceGroupIndex" : 0
		},
		{
			"backtrace" : 3,
			"compileGroupIndex" : 0,
			"path" : "storage/innobase/row/row0ext.cc",
			"sourceGroupIndex" : 0
		},
		{
			"backtrace" : 3,
			"compileGroupIndex" : 0,
			"path" : "storage/innobase/row/row0ftsort.cc",
			"sourceGroupIndex" : 0
		},
		{
			"backtrace" : 3,
			"compileGroupIndex" : 0,
			"path" : "storage/innobase/row/row0import.cc",
			"sourceGroupIndex" : 0
		},
		{
			"backtrace" : 3,
			"compileGroupIndex" : 0,
			"path" : "storage/innobase/row/row0ins.cc",
			"sourceGroupIndex" : 0
		},
		{
			"backtrace" : 3,
			"compileGroupIndex" : 0,
			"path" : "storage/innobase/row/row0merge.cc",
			"sourceGroupIndex" : 0
		},
		{
			"backtrace" : 3,
			"compileGroupIndex" : 0,
			"path" : "storage/innobase/row/row0mysql.cc",
			"sourceGroupIndex" : 0
		},
		{
			"backtrace" : 3,
			"compileGroupIndex" : 0,
			"path" : "storage/innobase/row/row0log.cc",
			"sourceGroupIndex" : 0
		},
		{
			"backtrace" : 3,
			"compileGroupIndex" : 0,
			"path" : "storage/innobase/row/row0purge.cc",
			"sourceGroupIndex" : 0
		},
		{
			"backtrace" : 3,
			"compileGroupIndex" : 0,
			"path" : "storage/innobase/row/row0row.cc",
			"sourceGroupIndex" : 0
		},
		{
			"backtrace" : 3,
			"compileGroupIndex" : 0,
			"path" : "storage/innobase/row/row0sel.cc",
			"sourceGroupIndex" : 0
		},
		{
			"backtrace" : 3,
			"compileGroupIndex" : 0,
			"path" : "storage/innobase/row/row0uins.cc",
			"sourceGroupIndex" : 0
		},
		{
			"backtrace" : 3,
			"compileGroupIndex" : 0,
			"path" : "storage/innobase/row/row0umod.cc",
			"sourceGroupIndex" : 0
		},
		{
			"backtrace" : 3,
			"compileGroupIndex" : 0,
			"path" : "storage/innobase/row/row0undo.cc",
			"sourceGroupIndex" : 0
		},
		{
			"backtrace" : 3,
			"compileGroupIndex" : 0,
			"path" : "storage/innobase/row/row0upd.cc",
			"sourceGroupIndex" : 0
		},
		{
			"backtrace" : 3,
			"compileGroupIndex" : 0,
			"path" : "storage/innobase/row/row0quiesce.cc",
			"sourceGroupIndex" : 0
		},
		{
			"backtrace" : 3,
			"compileGroupIndex" : 0,
			"path" : "storage/innobase/row/row0vers.cc",
			"sourceGroupIndex" : 0
		},
		{
			"backtrace" : 3,
			"compileGroupIndex" : 0,
			"path" : "storage/innobase/srv/srv0conc.cc",
			"sourceGroupIndex" : 0
		},
		{
			"backtrace" : 3,
			"compileGroupIndex" : 0,
			"path" : "storage/innobase/srv/srv0mon.cc",
			"sourceGroupIndex" : 0
		},
		{
			"backtrace" : 3,
			"compileGroupIndex" : 0,
			"path" : "storage/innobase/srv/srv0srv.cc",
			"sourceGroupIndex" : 0
		},
		{
			"backtrace" : 3,
			"compileGroupIndex" : 0,
			"path" : "storage/innobase/srv/srv0start.cc",
			"sourceGroupIndex" : 0
		},
		{
			"backtrace" : 3,
			"compileGroupIndex" : 0,
			"path" : "storage/innobase/sync/sync0arr.cc",
			"sourceGroupIndex" : 0
		},
		{
			"backtrace" : 3,
			"compileGroupIndex" : 0,
			"path" : "storage/innobase/sync/sync0rw.cc",
			"sourceGroupIndex" : 0
		},
		{
			"backtrace" : 3,
			"compileGroupIndex" : 0,
			"path" : "storage/innobase/sync/sync0sync.cc",
			"sourceGroupIndex" : 0
		},
		{
			"backtrace" : 3,
			"compileGroupIndex" : 0,
			"path" : "storage/innobase/trx/trx0i_s.cc",
			"sourceGroupIndex" : 0
		},
		{
			"backtrace" : 3,
			"compileGroupIndex" : 0,
			"path" : "storage/innobase/trx/trx0purge.cc",
			"sourceGroupIndex" : 0
		},
		{
			"backtrace" : 3,
			"compileGroupIndex" : 0,
			"path" : "storage/innobase/trx/trx0rec.cc",
			"sourceGroupIndex" : 0
		},
		{
			"backtrace" : 3,
			"compileGroupIndex" : 0,
			"path" : "storage/innobase/trx/trx0roll.cc",
			"sourceGroupIndex" : 0
		},
		{
			"backtrace" : 3,
			"compileGroupIndex" : 0,
			"path" : "storage/innobase/trx/trx0rseg.cc",
			"sourceGroupIndex" : 0
		},
		{
			"backtrace" : 3,
			"compileGroupIndex" : 0,
			"path" : "storage/innobase/trx/trx0sys.cc",
			"sourceGroupIndex" : 0
		},
		{
			"backtrace" : 3,
			"compileGroupIndex" : 0,
			"path" : "storage/innobase/trx/trx0trx.cc",
			"sourceGroupIndex" : 0
		},
		{
			"backtrace" : 3,
			"compileGroupIndex" : 0,
			"path" : "storage/innobase/trx/trx0undo.cc",
			"sourceGroupIndex" : 0
		},
		{
			"backtrace" : 3,
			"compileGroupIndex" : 0,
			"path" : "storage/innobase/usr/usr0sess.cc",
			"sourceGroupIndex" : 0
		},
		{
			"backtrace" : 3,
			"compileGroupIndex" : 0,
			"path" : "storage/innobase/ut/ut0bh.cc",
			"sourceGroupIndex" : 0
		},
		{
			"backtrace" : 3,
			"compileGroupIndex" : 0,
			"path" : "storage/innobase/ut/ut0byte.cc",
			"sourceGroupIndex" : 0
		},
		{
			"backtrace" : 3,
			"compileGroupIndex" : 0,
			"path" : "storage/innobase/ut/ut0crc32.cc",
			"sourceGroupIndex" : 0
		},
		{
			"backtrace" : 3,
			"compileGroupIndex" : 0,
			"path" : "storage/innobase/ut/ut0dbg.cc",
			"sourceGroupIndex" : 0
		},
		{
			"backtrace" : 3,
			"compileGroupIndex" : 0,
			"path" : "storage/innobase/ut/ut0list.cc",
			"sourceGroupIndex" : 0
		},
		{
			"backtrace" : 3,
			"compileGroupIndex" : 0,
			"path" : "storage/innobase/ut/ut0mem.cc",
			"sourceGroupIndex" : 0
		},
		{
			"backtrace" : 3,
			"compileGroupIndex" : 0,
			"path" : "storage/innobase/ut/ut0rbt.cc",
			"sourceGroupIndex" : 0
		},
		{
			"backtrace" : 3,
			"compileGroupIndex" : 0,
			"path" : "storage/innobase/ut/ut0rnd.cc",
			"sourceGroupIndex" : 0
		},
		{
			"backtrace" : 3,
			"compileGroupIndex" : 0,
			"path" : "storage/innobase/ut/ut0ut.cc",
			"sourceGroupIndex" : 0
		},
		{
			"backtrace" : 3,
			"compileGroupIndex" : 0,
			"path" : "storage/innobase/ut/ut0vec.cc",
			"sourceGroupIndex" : 0
		},
		{
			"backtrace" : 3,
			"compileGroupIndex" : 0,
			"path" : "storage/innobase/ut/ut0wqueue.cc",
			"sourceGroupIndex" : 0
		}
	],
	"type" : "STATIC_LIBRARY"
}
